Metadata-Version: 2.1
Name: classforge
Version: 0.9
Summary: A new python object system
Home-page: https://classforge.io
Author: Michael DeHaan
Author-email: michael@michaeldehaan.net
License: UNKNOWN
Platform: UNKNOWN
Classifier: Programming Language :: Python :: 3
Classifier: Development Status :: 4 - Beta
Classifier: License :: OSI Approved :: MIT License
Classifier: Intended Audience :: Developers
Classifier: Topic :: Software Development
Requires-Python: >=3.6
